application/__init__.py
application/application.py
application/config.py
application/docker.py
application/docker_cli.py
application/logger.py
application/parser.py
docker_compose_multistage-0.1.data/scripts/docker-compose-multistage
docker_compose_multistage-0.1.dist-info/LICENSE
docker_compose_multistage-0.1.dist-info/METADATA
docker_compose_multistage-0.1.dist-info/WHEEL
docker_compose_multistage-0.1.dist-info/top_level.txt
docker_compose_multistage-0.1.dist-info/RECORD
