Metadata-Version: 2.1
Name: docker-compose-multistage
Version: 0.1
Summary: A Docker utility package to separately push each stage of dockerfiles
Home-page: https://github.com/sancherie/docker-multistage-pusher
Author: Clément SANCHEZ
Author-email: clement@sanchez.sh
License: UNKNOWN
Platform: UNKNOWN
Classifier: Programming Language :: Python :: 3
Classifier: License :: OSI Approved :: MIT License
Classifier: Operating System :: OS Independent
